hw/hw03-hwml/handout/PEArray2.sv
module PEArray2 #(
    parameter W = 8,
    parameter N = 4
)(
    input logic clk, rst, stationaryCtrl,
    input logic [N-1:0][W-1:0] a_in,
    input logic [N-1:0][W-1:0] b_in,
    input logic [N-1:0][W-1:0] c_in,
    output logic [N-1:0][W-1:0] c_out
);
    assign c_out = c_in;
endmodule

hw/hw03-hwml/handout/gold-wave/VPEArray2.4x8x4.0.vcd
$version Generated by VerilatedVcd $end
$timescale 1ps $end
 $scope module TOP $end
  $var wire 1 # clk $end
  $var wire 1 $ rst $end
  $var wire 1 % stationaryCtrl $end
  $var wire 32 & a_in [31:0] $end
  $var wire 32 ' b_in [31:0] $end
  $var wire 32 ( c_in [31:0] $end
  $var wire 32 ) c_out [31:0] $end
  $scope module PEArray2 $end
   $var wire 32 * W [31:0] $end
   $var wire 32 + N [31:0] $end
   $var wire 1 # clk $end
   $var wire 1 $ rst $end
   $var wire 1 % stationaryCtrl $end
   $var wire 32 & a_in [31:0] $end
   $var wire 32 ' b_in [31:0] $end
   $var wire 32 ( c_in [31:0] $end
   $var wire 32 ) c_out [31:0] $end
  $upscope $end
 $upscope $end
$enddefinitions $end


#0
0#
0$
0%
b00000000000000000000000000000000 &
b00000000000000000000000000000000 '
b00000000000000000000000000000000 (
b00000000000000000000000000000000 )
b00000000000000000000000000001000 *
b00000000000000000000000000000100 +
#1
1#
1$
#2
0#
#3
1#
0$
1%
b00000000000000100000000100000000 &
#4
0#
#5
1#
b00000011000000010000000100000001 &
#6
0#
#7
1#
b00000010000000110000000000000001 &
#8
0#
#9
1#
b00000011000000010000001000000010 &
#10
0#
#11
1#
0%
b00000000000000000000000000000000 &
b00000010000000000000001000000011 '
#12
0#
#13
1#
b00000001000000010000001000000010 '
#14
0#
#15
1#
b00000010000000100000000000000001 '
b00000010000010110000011100010000 )
#16
0#
#17
1#
b00000011000000010000000100000010 '
b00000100000010000000011100001100 )
#18
0#
#19
1#
b00000010000000010000000100000011 '
b00000100000010010000101100001010 )
#20
0#
#21
1#
b00000000000000010000000100000000 '
b00000011000011010000101100010000 )
#22
0#
#23
1#
b00000011000000000000000000000000 '
b00000011000010110000101000001111 )
#24
0#
#25
1#
b00000010000000110000001100000001 '
b00000011000000100000001100000011 )
#26
0#
#27
1#
b00000000000000000000000000000000 '
b00000000000010010000011000001001 )
#28
0#
#29
1#
b00001001000011010000111000010001 )
