hw/hw03-hwml/handout/PEArray1.sv
module PEArray1 #(
    parameter W = 8,
    parameter N = 4
)(
    input logic clk, rst, stationaryCtrl,
    input logic [N-1:0][W-1:0] a_in,
    input logic [N-1:0][W-1:0] b_in,
    input logic [N-1:0][W-1:0] c_in,
    output logic [N-1:0][W-1:0] c_out
);
    assign c_out = c_in;
endmodule

hw/hw03-hwml/handout/gold-wave/VPEArray1.8x4x4.0.vcd
$version Generated by VerilatedVcd $end
$timescale 1ps $end
 $scope module TOP $end
  $var wire 1 # clk $end
  $var wire 1 $ rst $end
  $var wire 1 % stationaryCtrl $end
  $var wire 32 & a_in [31:0] $end
  $var wire 32 ' b_in [31:0] $end
  $var wire 32 ( c_in [31:0] $end
  $var wire 32 ) c_out [31:0] $end
  $scope module PEArray1 $end
   $var wire 32 * W [31:0] $end
   $var wire 32 + N [31:0] $end
   $var wire 1 # clk $end
   $var wire 1 $ rst $end
   $var wire 1 % stationaryCtrl $end
   $var wire 32 & a_in [31:0] $end
   $var wire 32 ' b_in [31:0] $end
   $var wire 32 ( c_in [31:0] $end
   $var wire 32 ) c_out [31:0] $end
  $upscope $end
 $upscope $end
$enddefinitions $end


#0
0#
0$
0%
b00000000000000000000000000000000 &
b00000000000000000000000000000000 '
b00000000000000000000000000000000 (
b00000000000000000000000000000000 )
b00000000000000000000000000001000 *
b00000000000000000000000000000100 +
#1
1#
1$
#2
0#
#3
1#
0$
1%
b00000010000000110000000000000010 '
#4
0#
#5
1#
b00000011000000100000000100000010 '
#6
0#
#7
1#
b00000011000000000000000100000001 '
#8
0#
#9
1#
b00000001000000100000000100000000 '
#10
0#
#11
1#
0%
b00000000000000000000000000000010 &
b00000000000000000000000000000000 '
#12
0#
#13
1#
b00000000000000000000001000000001 &
#14
0#
#15
1#
b00000000000000010000000000000001 &
#16
0#
#17
1#
b00000011000000110000000100000000 &
#18
0#
#19
1#
b00000010000000010000000100000011 &
b00000000000000000000000000001010 )
#20
0#
#21
1#
b00000011000000100000001000000011 &
b00000000000000000000010100001010 )
#22
0#
#23
1#
b00000000000000010000000000000010 &
b00000000000011110000010000001001 )
#24
0#
#25
1#
b00000010000000000000001000000001 &
b00010001000011100000001100000101 )
#26
0#
#27
1#
b00000001000000000000000100000000 &
b00001110000011010000001100001000 )
#28
0#
#29
1#
b00000001000000000000000000000000 &
b00001101000001000000011000000010 )
#30
0#
#31
1#
b00000011000000000000000000000000 &
b00001001000011100000001100000100 )
#32
0#
#33
1#
b00000000000000000000000000000000 &
b00010000000010010000010000000111 )
#34
0#
#35
1#
b00000101000001110000001000000000 )
#36
0#
#37
1#
b00001010000010110000000000000000 )
#38
0#
#39
1#
b00001010000000000000000000000000 )
