hw/hw03-hwml/handout/PEArray2.sv
module PEArray2 #(
    parameter W = 8,
    parameter N = 4
)(
    input logic clk, rst, stationaryCtrl,
    input logic [N-1:0][W-1:0] a_in,
    input logic [N-1:0][W-1:0] b_in,
    input logic [N-1:0][W-1:0] c_in,
    output logic [N-1:0][W-1:0] c_out
);
    assign c_out = c_in;
endmodule

hw/hw03-hwml/handout/gold-wave/VPEArray2.16x9x16.0.vcd
$version Generated by VerilatedVcd $end
$timescale 1ps $end
 $scope module TOP $end
  $var wire 1 # clk $end
  $var wire 1 $ rst $end
  $var wire 1 % stationaryCtrl $end
  $var wire 32 & a_in [31:0] $end
  $var wire 32 ' b_in [31:0] $end
  $var wire 32 ( c_in [31:0] $end
  $var wire 32 ) c_out [31:0] $end
  $scope module PEArray2 $end
   $var wire 32 * W [31:0] $end
   $var wire 32 + N [31:0] $end
   $var wire 1 # clk $end
   $var wire 1 $ rst $end
   $var wire 1 % stationaryCtrl $end
   $var wire 32 & a_in [31:0] $end
   $var wire 32 ' b_in [31:0] $end
   $var wire 32 ( c_in [31:0] $end
   $var wire 32 ) c_out [31:0] $end
  $upscope $end
 $upscope $end
$enddefinitions $end


#0
0#
0$
0%
b00000000000000000000000000000000 &
b00000000000000000000000000000000 '
b00000000000000000000000000000000 (
b00000000000000000000000000000000 )
b00000000000000000000000000001000 *
b00000000000000000000000000000100 +
#1
1#
1$
#2
0#
#3
1#
0$
1%
b00000000000000010000001100000000 &
#4
0#
#5
1#
b00000001000000110000000000000011 &
#6
0#
#7
1#
b00000010000000110000001100000000 &
#8
0#
#9
1#
b00000010000000000000000000000000 &
#10
0#
#11
1#
0%
b00000000000000000000000000000000 &
b00000001000000100000001000000001 '
#12
0#
#13
1#
b00000001000000010000000000000010 '
#14
0#
#15
1#
b00000011000000100000001000000010 '
b00001000000010100000111000000010 )
#16
0#
#17
1#
b00000000000000100000000000000010 '
b00000001000010100000010100000010 )
#18
0#
#19
1#
b00000010000000110000001000000000 '
b00001000000011110001001000000110 )
#20
0#
#21
1#
b00000010000000100000001000000001 '
b00000010000011000000011000000000 )
#22
0#
#23
1#
b00000011000000110000001000000010 '
b00001001000010110001001100000100 )
#24
0#
#25
1#
b00000000000000000000000000000000 '
b00001000000010110001000000000100 )
#26
0#
#27
1#
b00000010000000110000000000000001 '
b00001001000100100001010100000110 )
#28
0#
#29
1#
b00000000000000000000000000000000 '
b00000000000000000000000000000000 )
#30
0#
#31
1#
b00000011000011100000110100000100 )
#32
0#
#33
1#
1%
b00000000000000110000001000000011 &
b00000000000000000000000000000000 )
#34
0#
#35
1#
b00000011000000100000000000000001 &
#36
0#
#37
1#
b00000011000000010000001100000000 &
#38
0#
#39
1#
b00000000000000000000000100000010 &
#40
0#
#41
1#
0%
b00000000000000000000000000000000 &
b00000011000000100000000100000000 '
b00001000000010100000111000000010 (
b00001000000010100000111000000010 )
#42
0#
#43
1#
b00000001000000000000001100000011 '
b00000001000010100000010100000010 (
b00000001000010100000010100000010 )
#44
0#
#45
1#
b00000010000000010000000000000010 '
b00001000000011110001001000000110 (
b00010000000111000010000000000111 )
#46
0#
#47
1#
b00000001000000010000001000000001 '
b00000010000011000000011000000000 (
b00010001000100100001001000001001 )
#48
0#
#49
1#
b00001001000010110001001100000100 (
b00010010000101010001101000001000 )
#50
0#
#51
1#
b00000001000000110000001000000010 '
b00001000000010110001000000000100 (
b00010010000100010001101000001000 )
#52
0#
#53
1#
b00000011000000010000000000000011 '
b00001001000100100001010100000110 (
b00010011000110000001111100001010 )
#54
0#
#55
1#
b00000011000000100000000000000001 '
b00000000000000000000000000000000 (
b00010011000010110000110000000110 )
#56
0#
#57
1#
b00000010000000010000000100000000 '
b00001100000011100000101000000110 )
#58
0#
#59
1#
b00000000000000000000000000000000 '
b00001001000011100000101100000010 )
#60
0#
#61
1#
b00000101000010000000101000000001 )
#62
0#
#63
1#
1%
b00000001000000110000000000000000 &
b00000000000000000000000000000000 )
#64
0#
#65
1#
b00000000000000000000001000000010 &
#66
0#
#67
1#
b00000010000000010000001000000001 &
#68
0#
#69
1#
b00000001000000000000001000000010 &
#70
0#
#71
1#
0%
b00000000000000000000000000000000 &
b00000010000000010000000000000001 '
b00010000000111000010000000000111 (
b00010000000111000010000000000111 )
#72
0#
#73
1#
b00000010000000110000001000000010 '
b00010001000100100001001000001001 (
b00010001000100100001001000001001 )
#74
0#
#75
1#
b00000010000000010000000100000011 '
b00010010000101010001101000001000 (
b00010111000101110010000000001100 )
#76
0#
#77
1#
b00000000000000110000000100000001 '
b00010010000100010001101000001000 (
b00011101000110010010011100010010 )
#78
0#
#79
1#
b00000011000000100000000100000000 '
b00010011000110000001111100001010 (
b00011000001000000010100100010100 )
#80
0#
#81
1#
b00000001000000100000000100000011 '
b00010011000010110000110000000110 (
b00011100000011110001001000001010 )
#82
0#
#83
1#
b00000011000000010000001000000010 '
b00001100000011100000101000000110 (
b00010101000100000001010000001011 )
#84
0#
#85
1#
b00000001000000110000001000000010 '
b00001001000011100000101100000010 (
b00010000000101100001010000001011 )
#86
0#
#87
1#
b00000001000000110000001100000001 '
b00000000000000000000000000000000 (
b00000110000010000000110100001011 )
#88
0#
#89
1#
b00000000000000000000000000000000 '
b00001010000010000000101100001001 )
#90
0#
#91
1#
b00001010000010000000110000001001 )
#92
0#
#93
1#
1%
b00000011000000100000001000000000 &
b00000000000000000000000000000000 )
#94
0#
#95
1#
b00000010000000000000000000000010 &
#96
0#
#97
1#
b00000001000000110000001100000000 &
#98
0#
#99
1#
b00000000000000000000000000000010 &
#100
0#
#101
1#
0%
b00000000000000000000000000000000 &
b00000011000000000000001000000010 '
b00010111000101110010000000001100 (
b00010111000101110010000000001100 )
#102
0#
#103
1#
b00000001000000000000001000000011 '
b00011101000110010010011100010010 (
b00011101000110010010011100010010 )
#104
0#
#105
1#
b00000001000000100000000100000011 '
b00011000001000000010100100010100 (
b00100101001010100011001000011000 )
#106
0#
#107
1#
b00000000000000000000000100000011 '
b00011100000011110001001000001010 (
b00100011000101110001100100010000 )
#108
0#
#109
1#
b00000000000000100000000000000011 '
b00010101000100000001010000001011 (
b00011110000110000001111000010001 )
#110
0#
#111
1#
b00000000000000010000000000000001 '
b00010000000101100001010000001011 (
b00010010000111000001011100010001 )
#112
0#
#113
1#
b00000011000000100000001000000001 '
b00000110000010000000110100001011 (
b00001010000011100001001100010001 )
#114
0#
#115
1#
b00000011000000100000001100000000 '
b00001010000010000000101100001001 (
b00001100000010100000111000001011 )
#116
0#
#117
1#
b00000011000000000000001100000010 '
b00000000000000000000000000000000 (
b00010001000010000000111100000010 )
#118
0#
#119
1#
b00000000000000000000000000000000 '
b00010011000001100001001000000000 )
#120
0#
#121
1#
b00001111000010100000110000000100 )
#122
0#
#123
1#
1%
b00000000000000100000001100000000 &
b00000000000000000000000000000000 )
#124
0#
#125
1#
b00000011000000100000000100000001 &
#126
0#
#127
1#
b00000010000000000000001000000011 &
#128
0#
#129
1#
b00000000000000010000000100000010 &
#130
0#
#131
1#
0%
b00000000000000000000000000000000 &
b00000001000000100000001000000001 '
#132
0#
#133
1#
b00000001000000010000000000000010 '
#134
0#
#135
1#
b00000011000000100000001000000010 '
b00001010000010100000100100000110 )
#136
0#
#137
1#
b00000000000000100000000000000010 '
b00000010000001110000100000000101 )
#138
0#
#139
1#
b00000010000000110000001000000000 '
b00001010000100010001000000001000 )
#140
0#
#141
1#
b00000010000000100000001000000001 '
b00000100000001100000011000000110 )
#142
0#
#143
1#
b00000011000000110000001000000010 '
b00001100000011100000100000000101 )
#144
0#
#145
1#
b00000000000000000000000000000000 '
b00001010000011010000101100000110 )
#146
0#
#147
1#
b00000010000000110000000000000001 '
b00001100000100110001000000001001 )
#148
0#
#149
1#
b00000000000000000000000000000000 '
b00000000000000000000000000000000 )
#150
0#
#151
1#
b00000110000011010000011100000101 )
#152
0#
#153
1#
1%
b00000000000000010000000100000011 &
b00000000000000000000000000000000 )
#154
0#
#155
1#
b00000001000000100000001000000000 &
#156
0#
#157
1#
b00000001000000100000000000000000 &
#158
0#
#159
1#
b00000011000000110000001100000001 &
#160
0#
#161
1#
0%
b00000000000000000000000000000000 &
b00000011000000100000000100000000 '
b00001010000010100000100100000110 (
b00001010000010100000100100000110 )
#162
0#
#163
1#
b00000001000000000000001100000011 '
b00000010000001110000100000000101 (
b00000010000001110000100000000101 )
#164
0#
#165
1#
b00000010000000010000000000000010 '
b00001010000100010001000000001000 (
b00001101000110100001011100011010 )
#166
0#
#167
1#
b00000001000000010000001000000001 '
b00000100000001100000011000000110 (
b00010000000011010000011100010101 )
#168
0#
#169
1#
b00001100000011100000100000000101 (
b00010011000100100000110000010000 )
#170
0#
#171
1#
b00000001000000110000001000000010 '
b00001010000011010000101100000110 (
b00010000000101000000111000010011 )
#172
0#
#173
1#
b00000011000000010000000000000011 '
b00001100000100110001000000001001 (
b00010010000110100001001100010110 )
#174
0#
#175
1#
b00000011000000100000000000000001 '
b00000000000000000000000000000000 (
b00001011000010110000011100010100 )
#176
0#
#177
1#
b00000010000000010000000100000000 '
b00001010000001010000010100001111 )
#178
0#
#179
1#
b00000000000000000000000000000000 '
b00000101000001110000011100010000 )
#180
0#
#181
1#
b00000010000001100000010000001100 )
#182
0#
#183
1#
1%
b00000010000000000000001100000010 &
b00000000000000000000000000000000 )
#184
0#
#185
1#
b00000010000000000000001000000010 &
#186
0#
#187
1#
b00000000000000100000000100000000 &
#188
0#
#189
1#
b00000011000000110000000000000001 &
#190
0#
#191
1#
0%
b00000000000000000000000000000000 &
b00000010000000010000000000000001 '
b00001101000110100001011100011010 (
b00001101000110100001011100011010 )
#192
0#
#193
1#
b00000010000000110000001000000010 '
b00010000000011010000011100010101 (
b00010000000011010000011100010101 )
#194
0#
#195
1#
b00000010000000010000000100000011 '
b00010011000100100000110000010000 (
b00011001000110000000111000011010 )
#196
0#
#197
1#
b00000000000000110000000100000001 '
b00010000000101000000111000010011 (
b00011110001000000001011000100100 )
#198
0#
#199
1#
b00000011000000100000000100000000 '
b00010010000110100001001100010110 (
b00011111001001100001011000100010 )
#200
0#
#201
1#
b00000001000000100000000100000011 '
b00001011000010110000011100010100 (
b00010000000011110000111000011110 )
#202
0#
#203
1#
b00000011000000010000001000000010 '
b00001010000001010000010100001111 (
b00010011000011010000101000011110 )
#204
0#
#205
1#
b00000001000000110000001000000010 '
b00000101000001110000011100010000 (
b00010000000100010000110000011100 )
#206
0#
#207
1#
b00000001000000110000001100000001 '
b00000000000000000000000000000000 (
b00010000000011100000010000001110 )
#208
0#
#209
1#
b00000000000000000000000000000000 '
b00001100000010100000100000001110 )
#210
0#
#211
1#
b00001101000010100000100100001101 )
#212
0#
#213
1#
1%
b00000001000000010000000000000011 &
b00000000000000000000000000000000 )
#214
0#
#215
1#
b00000000000000110000000100000001 &
#216
0#
#217
1#
b00000010000000000000000000000000 &
#218
0#
#219
1#
b00000000000000010000001100000000 &
#220
0#
#221
1#
0%
b00000000000000000000000000000000 &
b00000011000000000000001000000010 '
b00011001000110000000111000011010 (
b00011001000110000000111000011010 )
#222
0#
#223
1#
b00000001000000000000001000000011 '
b00011110001000000001011000100100 (
b00011110001000000001011000100100 )
#224
0#
#225
1#
b00000001000000100000000100000011 '
b00011111001001100001011000100010 (
b00101000001010100001110000101000 )
#226
0#
#227
1#
b00000000000000000000000100000011 '
b00010000000011110000111000011110 (
b00011010000101000001000000100100 )
#228
0#
#229
1#
b00000000000000100000000000000011 '
b00010011000011010000101000011110 (
b00011111000101110000110000100011 )
#230
0#
#231
1#
b00000000000000010000000000000001 '
b00010000000100010000110000011100 (
b00011001000101010000110000011111 )
#232
0#
#233
1#
b00000011000000100000001000000001 '
b00010000000011100000010000001110 (
b00011011000101110000010000010000 )
#234
0#
#235
1#
b00000011000000100000001100000000 '
b00001100000010100000100000001110 (
b00010000000011100000100000001111 )
#236
0#
#237
1#
b00000011000000000000001100000010 '
b00000000000000000000000000000000 (
b00001000000010010000011000001000 )
#238
0#
#239
1#
b00000000000000000000000000000000 '
b00000101000010010000011000001011 )
#240
0#
#241
1#
b00001001000001010000011000001001 )
#242
0#
#243
1#
1%
b00000000000000000000000100000010 &
b00000000000000000000000000000000 )
#244
0#
#245
1#
b00000001000000000000001000000011 &
#246
0#
#247
1#
b00000000000000000000000100000000 &
#248
0#
#249
1#
b00000001000000000000001100000001 &
#250
0#
#251
1#
0%
b00000000000000000000000000000000 &
b00000001000000100000001000000001 '
#252
0#
#253
1#
b00000001000000010000000000000010 '
#254
0#
#255
1#
b00000011000000100000001000000010 '
b00000100000010000000001000001000 )
#256
0#
#257
1#
b00000000000000100000000000000010 '
b00000100000001110000000000000011 )
#258
0#
#259
1#
b00000010000000110000001000000000 '
b00000110000011010000001000001011 )
#260
0#
#261
1#
b00000010000000100000001000000001 '
b00000100000001100000000000000010 )
#262
0#
#263
1#
b00000011000000110000001000000010 '
b00000010000001100000001000001000 )
#264
0#
#265
1#
b00000000000000000000000000000000 '
b00000100000010010000001000001001 )
#266
0#
#267
1#
b00000010000000110000000000000001 '
b00000110000011010000001000001011 )
#268
0#
#269
1#
b00000000000000000000000000000000 '
b00000000000000000000000000000000 )
#270
0#
#271
1#
b00000010000001010000000000000011 )
#272
0#
#273
1#
1%
b00000001000000010000000000000011 &
b00000000000000000000000000000000 )
#274
0#
#275
1#
b00000001000000000000001000000000 &
#276
0#
#277
1#
b00000000000000000000001000000010 &
#278
0#
#279
1#
b00000011000000100000001000000001 &
#280
0#
#281
1#
0%
b00000000000000000000000000000000 &
b00000011000000100000000100000000 '
b00000100000010000000001000001000 (
b00000100000010000000001000001000 )
#282
0#
#283
1#
b00000001000000000000001100000011 '
b00000100000001110000000000000011 (
b00000100000001110000000000000011 )
#284
0#
#285
1#
b00000010000000010000000000000010 '
b00000110000011010000001000001011 (
b00001011000100100000010000011010 )
#286
0#
#287
1#
b00000001000000010000001000000001 '
b00000100000001100000000000000010 (
b00001110000011010000110000001110 )
#288
0#
#289
1#
b00000010000001100000001000001000 (
b00001011000010000000011000010010 )
#290
0#
#291
1#
b00000001000000110000001000000010 '
b00000100000010010000001000001001 (
b00001001000011100000100000010011 )
#292
0#
#293
1#
b00000011000000010000000000000011 '
b00000110000011010000001000001011 (
b00001011000100100000100000010101 )
#294
0#
#295
1#
b00000011000000100000000000000001 '
b00000000000000000000000000000000 (
b00001010000001010000100000001111 )
#296
0#
#297
1#
b00000010000000010000000100000000 '
b00001101000000110000011000001110 )
#298
0#
#299
1#
b00000000000000000000000000000000 '
b00001000000000110000001000001110 )
#300
0#
#301
1#
b00000011000001000000001000001010 )
#302
0#
#303
1#
1%
b00000001000000100000000000000000 &
b00000000000000000000000000000000 )
#304
0#
#305
1#
b00000001000000110000001000000001 &
#306
0#
#307
1#
b00000001000000110000000000000001 &
#308
0#
#309
1#
b00000010000000100000001000000000 &
#310
0#
#311
1#
0%
b00000000000000000000000000000000 &
b00000010000000010000000000000001 '
b00001011000100100000010000011010 (
b00001011000100100000010000011010 )
#312
0#
#313
1#
b00000010000000110000001000000010 '
b00001110000011010000110000001110 (
b00001110000011010000110000001110 )
#314
0#
#315
1#
b00000010000000010000000100000011 '
b00001011000010000000011000010010 (
b00001111000011100000110000011000 )
#316
0#
#317
1#
b00000000000000110000000100000001 '
b00001001000011100000100000010011 (
b00010001000111110001010100100001 )
#318
0#
#319
1#
b00000011000000100000000100000000 '
b00001011000100100000100000010101 (
b00001111000111000001000000011101 )
#320
0#
#321
1#
b00000001000000100000000100000011 '
b00001010000001010000100000001111 (
b00010000000100010001001000010111 )
#322
0#
#323
1#
b00000011000000010000001000000010 '
b00001101000000110000011000001110 (
b00010100000011100000111100011010 )
#324
0#
#325
1#
b00000001000000110000001000000010 '
b00001000000000110000001000001110 (
b00001101000011110000110000010110 )
#326
0#
#327
1#
b00000001000000110000001100000001 '
b00000000000000000000000000000000 (
b00000101000011000000100000001100 )
#328
0#
#329
1#
b00000000000000000000000000000000 '
b00000111000100000000110000001100 )
#330
0#
#331
1#
b00000111000100010000101100001110 )
#332
0#
#333
1#
1%
b00000011000000000000000000000000 &
b00000000000000000000000000000000 )
#334
0#
#335
1#
b00000000000000010000000100000011 &
#336
0#
#337
1#
b00000010000000100000000000000001 &
#338
0#
#339
1#
b00000000000000100000000100000000 &
#340
0#
#341
1#
0%
b00000000000000000000000000000000 &
b00000011000000000000001000000010 '
b00001111000011100000110000011000 (
b00001111000011100000110000011000 )
#342
0#
#343
1#
b00000001000000000000001000000011 '
b00010001000111110001010100100001 (
b00010001000111110001010100100001 )
#344
0#
#345
1#
b00000001000000100000000100000011 '
b00001111000111000001000000011101 (
b00011000001001000001100000011111 )
#346
0#
#347
1#
b00000000000000000000000100000011 '
b00010000000100010001001000010111 (
b00010011000111000001011100011001 )
#348
0#
#349
1#
b00000000000000100000000000000011 '
b00010100000011100000111100011010 (
b00010111000110100001100000011111 )
#350
0#
#351
1#
b00000000000000010000000000000001 '
b00001101000011110000110000010110 (
b00001101000110010000111100010111 )
#352
0#
#353
1#
b00000011000000100000001000000001 '
b00000101000011000000100000001100 (
b00000101000101110000111100010000 )
#354
0#
#355
1#
b00000011000000100000001100000000 '
b00000111000100000000110000001100 (
b00000111000101000000111100001110 )
#356
0#
#357
1#
b00000011000000000000001100000010 '
b00000000000000000000000000000000 (
b00001001000001110000101100000110 )
#358
0#
#359
1#
b00000000000000000000000000000000 '
b00001001000001010000101000000111 )
#360
0#
#361
1#
b00001001000010010000100000000011 )
#362
0#
#363
1#
1%
b00000000000000100000000100000001 &
b00000000000000000000000000000000 )
#364
0#
#365
1#
b00000011000000100000000000000001 &
#366
0#
#367
1#
b00000010000000110000001100000011 &
#368
0#
#369
1#
b00000010000000000000000000000010 &
#370
0#
#371
1#
0%
b00000000000000000000000000000000 &
b00000001000000100000001000000001 '
#372
0#
#373
1#
b00000001000000010000000000000010 '
#374
0#
#375
1#
b00000011000000100000001000000010 '
b00000111000010000001000100000100 )
#376
0#
#377
1#
b00000000000000100000000000000010 '
b00000100000001110000101100000110 )
#378
0#
#379
1#
b00000010000000110000001000000000 '
b00001000000011110001100000001010 )
#380
0#
#381
1#
b00000010000000100000001000000001 '
b00000110000001100000110000000100 )
#382
0#
#383
1#
b00000011000000110000001000000010 '
b00001000000011000001001100000100 )
#384
0#
#385
1#
b00000000000000000000000000000000 '
b00000111000010110001001100000110 )
#386
0#
#387
1#
b00000010000000110000000000000001 '
b00001010000100010001101100001010 )
#388
0#
#389
1#
b00000000000000000000000000000000 '
b00000000000000000000000000000000 )
#390
0#
#391
1#
b00000111000011010001000000000110 )
#392
0#
#393
1#
1%
b00000001000000000000001000000001 &
b00000000000000000000000000000000 )
#394
0#
#395
1#
b00000000000000110000000100000001 &
#396
0#
#397
1#
b00000011000000110000000000000011 &
#398
0#
#399
1#
b00000011000000110000000100000010 &
#400
0#
#401
1#
0%
b00000000000000000000000000000000 &
b00000011000000100000000100000000 '
b00000111000010000001000100000100 (
b00000111000010000001000100000100 )
#402
0#
#403
1#
b00000001000000000000001100000011 '
b00000100000001110000101100000110 (
b00000100000001110000101100000110 )
#404
0#
#405
1#
b00000010000000010000000000000010 '
b00001000000011110001100000001010 (
b00001101000101100010011100011010 )
#406
0#
#407
1#
b00000001000000010000001000000001 '
b00000110000001100000110000000100 (
b00010000000011000001100000010000 )
#408
0#
#409
1#
b00001000000011000001001100000100 (
b00001100000100010010001000010001 )
#410
0#
#411
1#
b00000001000000110000001000000010 '
b00000111000010110001001100000110 (
b00001101000100010001110000010000 )
#412
0#
#413
1#
b00000011000000010000000000000011 '
b00001010000100010001101100001010 (
b00010000000101110010010000010100 )
#414
0#
#415
1#
b00000011000000100000000000000001 '
b00000000000000000000000000000000 (
b00000111000011010001001000010010 )
#416
0#
#417
1#
b00000010000000010000000100000000 '
b00000110000001100001010100010010 )
#418
0#
#419
1#
b00000000000000000000000000000000 '
b00000100000001110001001000010001 )
#420
0#
#421
1#
b00000100000001000000100100001010 )
#422
0#
#423
1#
1%
b00000001000000010000000100000011 &
b00000000000000000000000000000000 )
#424
0#
#425
1#
b00000000000000110000001100000000 &
#426
0#
#427
1#
b00000000000000010000000100000000 &
#428
0#
#429
1#
b00000011000000000000001000000011 &
#430
0#
#431
1#
0%
b00000000000000000000000000000000 &
b00000010000000010000000000000001 '
b00001101000101100010011100011010 (
b00001101000101100010011100011010 )
#432
0#
#433
1#
b00000010000000110000001000000010 '
b00010000000011000001100000010000 (
b00010000000011000001100000010000 )
#434
0#
#435
1#
b00000010000000010000000100000011 '
b00001100000100010010001000010001 (
b00010010000101000010001100011010 )
#436
0#
#437
1#
b00000000000000110000000100000001 '
b00001101000100010001110000010000 (
b00011010001000000010000100100000 )
#438
0#
#439
1#
b00000011000000100000000100000000 '
b00010000000101110010010000010100 (
b00011101000111010010011000100101 )
#440
0#
#441
1#
b00000001000000100000000100000011 '
b00000111000011010001001000010010 (
b00001110000110010001011000010111 )
#442
0#
#443
1#
b00000011000000010000001000000010 '
b00000110000001100001010100010010 (
b00001100000011110001100000011101 )
#444
0#
#445
1#
b00000001000000110000001000000010 '
b00000100000001110001001000010001 (
b00010001000100000001010100011111 )
#446
0#
#447
1#
b00000001000000110000001100000001 '
b00000000000000000000000000000000 (
b00001100000010010000001100010011 )
#448
0#
#449
1#
b00000000000000000000000000000000 '
b00001100000011110000010100001101 )
#450
0#
#451
1#
b00001010000100100000011000001100 )
#452
0#
#453
1#
1%
b00000011000000000000000100000010 &
b00000000000000000000000000000000 )
#454
0#
#455
1#
b00000000000000100000001000000001 &
#456
0#
#457
1#
b00000011000000110000000100000001 &
#458
0#
#459
1#
b00000010000000110000000100000000 &
#460
0#
#461
1#
0%
b00000000000000000000000000000000 &
b00000011000000000000001000000010 '
b00010010000101000010001100011010 (
b00010010000101000010001100011010 )
#462
0#
#463
1#
b00000001000000000000001000000011 '
b00011010001000000010000100100000 (
b00011010001000000010000100100000 )
#464
0#
#465
1#
b00000001000000100000000100000011 '
b00011101000111010010011000100101 (
b00101100001000110011001100101101 )
#466
0#
#467
1#
b00000000000000000000000100000011 '
b00001110000110010001011000010111 (
b00011001001000000001111000011011 )
#468
0#
#469
1#
b00000000000000100000000000000011 '
b00001100000011110001100000011101 (
b00010110000110000010010100100110 )
#470
0#
#471
1#
b00000000000000010000000000000001 '
b00010001000100000001010100011111 (
b00011000000101010001100100100000 )
#472
0#
#473
1#
b00000011000000100000001000000001 '
b00001100000010010000001100010011 (
b00010010000100000000110000011001 )
#474
0#
#475
1#
b00000011000000100000001100000000 '
b00001100000011110000010100001101 (
b00001110000100100000100100010000 )
#476
0#
#477
1#
b00000011000000000000001100000010 '
b00000000000000000000000000000000 (
b00001101000010010001001000001110 )
#478
0#
#479
1#
b00000000000000000000000000000000 '
b00001100000010100001001000001111 )
#480
0#
#481
1#
b00010000000010000000111000001001 )
