hw/hw03-hwml/handout/PEArray1.sv
module PEArray1 #(
    parameter W = 8,
    parameter N = 4
)(
    input logic clk, rst, stationaryCtrl,
    input logic [N-1:0][W-1:0] a_in,
    input logic [N-1:0][W-1:0] b_in,
    input logic [N-1:0][W-1:0] c_in,
    output logic [N-1:0][W-1:0] c_out
);
    assign c_out = c_in;
endmodule

hw/hw03-hwml/handout/gold-wave/VPEArray1.8x8x8.0.vcd
$version Generated by VerilatedVcd $end
$timescale 1ps $end
 $scope module TOP $end
  $var wire 1 # clk $end
  $var wire 1 $ rst $end
  $var wire 1 % stationaryCtrl $end
  $var wire 32 & a_in [31:0] $end
  $var wire 32 ' b_in [31:0] $end
  $var wire 32 ( c_in [31:0] $end
  $var wire 32 ) c_out [31:0] $end
  $scope module PEArray1 $end
   $var wire 32 * W [31:0] $end
   $var wire 32 + N [31:0] $end
   $var wire 1 # clk $end
   $var wire 1 $ rst $end
   $var wire 1 % stationaryCtrl $end
   $var wire 32 & a_in [31:0] $end
   $var wire 32 ' b_in [31:0] $end
   $var wire 32 ( c_in [31:0] $end
   $var wire 32 ) c_out [31:0] $end
  $upscope $end
 $upscope $end
$enddefinitions $end


#0
0#
0$
0%
b00000000000000000000000000000000 &
b00000000000000000000000000000000 '
b00000000000000000000000000000000 (
b00000000000000000000000000000000 )
b00000000000000000000000000001000 *
b00000000000000000000000000000100 +
#1
1#
1$
#2
0#
#3
1#
0$
1%
b00000010000000000000000000000010 '
#4
0#
#5
1#
b00000000000000000000000000000011 '
#6
0#
#7
1#
b00000001000000100000001100000000 '
#8
0#
#9
1#
b00000000000000100000001100000011 '
#10
0#
#11
1#
0%
b00000000000000000000000000000011 &
b00000000000000000000000000000000 '
#12
0#
#13
1#
b00000000000000000000000000000010 &
#14
0#
#15
1#
b00000000000000000000001100000010 &
#16
0#
#17
1#
b00000010000000000000001000000011 &
#18
0#
#19
1#
b00000000000000100000000100000001 &
b00000000000000000000000000001101 )
#20
0#
#21
1#
b00000011000000010000000000000000 &
b00000000000000000000100100000110 )
#22
0#
#23
1#
b00000010000000100000000100000001 &
b00000000000001100000111100010010 )
#24
0#
#25
1#
b00000001000000110000001100000010 &
b00000100000010100000110000010000 )
#26
0#
#27
1#
b00000001000000110000001100000000 &
b00000011000010000000110000001011 )
#28
0#
#29
1#
b00000000000000110000000000000000 &
b00001000000010000000001100001011 )
#30
0#
#31
1#
b00000000000000000000000000000000 &
b00000101000000100000001100001100 )
#32
0#
#33
1#
b00000010000000100000110000001111 )
#34
0#
#35
1#
b00000011000010000000111100000000 )
#36
0#
#37
1#
b00000011000010100000000000000000 )
#38
0#
#39
1#
b00000011000000000000000000000000 )
#40
0#
#41
1#
1%
b00000011000000110000000000000000 '
b00000000000000000000000000000000 )
#42
0#
#43
1#
b00000000000000100000000100000011 '
#44
0#
#45
1#
b00000001000000100000001100000011 '
#46
0#
#47
1#
b00000000000000110000000100000011 '
#48
0#
#49
1#
0%
b00000000000000000000000000000000 '
b00000000000000000000000000001101 (
#50
0#
#51
1#
b00000000000000000000100100000110 (
#52
0#
#53
1#
b00000000000000110000000000000011 &
b00000000000001100000111100010010 (
#54
0#
#55
1#
b00000011000000110000001000000001 &
b00000100000010100000110000010000 (
b00000000000000000000000000001101 )
#56
0#
#57
1#
b00000000000000100000000000000001 &
b00000011000010000000110000001011 (
b00000000000000000000100100001111 )
#58
0#
#59
1#
b00000010000000000000000100000001 &
b00001000000010000000001100001011 (
b00000000000001100001001000011011 )
#60
0#
#61
1#
b00000000000000000000001100000001 &
b00000101000000100000001100001100 (
b00000100000110010000111100100101 )
#62
0#
#63
1#
b00000011000000010000000100000000 &
b00000010000000100000110000001111 (
b00001100000011100001011100001110 )
#64
0#
#65
1#
b00000011000000100000001100000000 &
b00000011000010000000111100000000 (
b00001000000111110000010000010001 )
#66
0#
#67
1#
b00000001000000000000000000000000 &
b00000011000010100000000000000000 (
b00001101000001010000011100011011 )
#68
0#
#69
1#
b00000000000000000000000000000000 (
b00000010000100000001011100011011 )
#70
0#
#71
1#
b00000000000000000000000000000000 &
b00001101000111000001010100001001 )
#72
0#
#73
1#
b00001111000101100000100100000000 )
#74
0#
#75
1#
b00000100000010010000000000000000 )
#76
0#
#77
1#
b00000110000000000000000000000000 )
#78
0#
#79
1#
1%
b00000011000000110000000000000011 '
b00000000000000000000000000000000 )
#80
0#
#81
1#
b00000000000000010000001000000001 '
#82
0#
#83
1#
b00000011000000010000001100000010 '
#84
0#
#85
1#
b00000001000000000000001100000000 '
#86
0#
#87
1#
0%
b00000000000000000000000000000011 &
b00000000000000000000000000000000 '
#88
0#
#89
1#
b00000000000000000000000000000010 &
#90
0#
#91
1#
b00000000000000000000001100000010 &
#92
0#
#93
1#
b00000010000000000000001000000011 &
#94
0#
#95
1#
b00000000000000100000000100000001 &
b00000000000000000000000000000110 )
#96
0#
#97
1#
b00000011000000010000000000000000 &
b00000000000000000000100100000110 )
#98
0#
#99
1#
b00000010000000100000000100000001 &
b00000000000001100000111100001111 )
#100
0#
#101
1#
b00000001000000110000001100000010 &
b00001001000000110001000000001001 )
#102
0#
#103
1#
b00000001000000110000001100000000 &
b00001011000011010000111000000101 )
#104
0#
#105
1#
b00000000000000110000000000000000 &
b00010001000010000000011100001000 )
#106
0#
#107
1#
b00000000000000000000000000000000 &
b00001100000001010000100100001001 )
#108
0#
#109
1#
b00000100000001110001001000001001 )
#110
0#
#111
1#
b00000110000001100001010100000000 )
#112
0#
#113
1#
b00001010000001100000000000000000 )
#114
0#
#115
1#
b00001011000000000000000000000000 )
#116
0#
#117
1#
1%
b00000000000000100000001000000001 '
b00000000000000000000000000000000 )
#118
0#
#119
1#
b00000001000000000000001100000011 '
#120
0#
#121
1#
b00000001000000010000001100000010 '
#122
0#
#123
1#
b00000000000000010000001100000000 '
#124
0#
#125
1#
0%
b00000000000000000000000000000000 '
b00000000000000000000000000000110 (
#126
0#
#127
1#
b00000000000000000000100100000110 (
#128
0#
#129
1#
b00000000000000110000000000000011 &
b00000000000001100000111100001111 (
#130
0#
#131
1#
b00000011000000110000001000000001 &
b00001001000000110001000000001001 (
b00000000000000000000000000000110 )
#132
0#
#133
1#
b00000000000000100000000000000001 &
b00001011000011010000111000000101 (
b00000000000000000000100100010010 )
#134
0#
#135
1#
b00000010000000000000000100000001 &
b00010001000010000000011100001000 (
b00000000000001100001111000011000 )
#136
0#
#137
1#
b00000000000000000000001100000001 &
b00001100000001010000100100001001 (
b00001001000010010001100100010101 )
#138
0#
#139
1#
b00000011000000010000000100000000 &
b00000100000001110001001000001001 (
b00001110000011010010011100000101 )
#140
0#
#141
1#
b00000011000000100000001100000000 &
b00000110000001100001010100000000 (
b00010100000100010000101000001101 )
#142
0#
#143
1#
b00000001000000000000000000000000 &
b00001010000001100000000000000000 (
b00010000000001100001010100010101 )
#144
0#
#145
1#
b00000000000000000000000000000000 (
b00000100000011110010011100010010 )
#146
0#
#147
1#
b00000000000000000000000000000000 &
b00000111000100000010001100000111 )
#148
0#
#149
1#
b00001110000010100000101100000000 )
#150
0#
#151
1#
b00000011000001010000000000000000 )
#152
0#
#153
1#
b00000011000000000000000000000000 )
