hw/hw03-hwml/handout/PEArray2.sv
module PEArray2 #(
    parameter W = 8,
    parameter N = 4
)(
    input logic clk, rst, stationaryCtrl,
    input logic [N-1:0][W-1:0] a_in,
    input logic [N-1:0][W-1:0] b_in,
    input logic [N-1:0][W-1:0] c_in,
    output logic [N-1:0][W-1:0] c_out
);
    assign c_out = c_in;
endmodule

hw/hw03-hwml/handout/gold-wave/VPEArray2.4x4x4.0.vcd
$version Generated by VerilatedVcd $end
$timescale 1ps $end
 $scope module TOP $end
  $var wire 1 # clk $end
  $var wire 1 $ rst $end
  $var wire 1 % stationaryCtrl $end
  $var wire 32 & a_in [31:0] $end
  $var wire 32 ' b_in [31:0] $end
  $var wire 32 ( c_in [31:0] $end
  $var wire 32 ) c_out [31:0] $end
  $scope module PEArray2 $end
   $var wire 32 * W [31:0] $end
   $var wire 32 + N [31:0] $end
   $var wire 1 # clk $end
   $var wire 1 $ rst $end
   $var wire 1 % stationaryCtrl $end
   $var wire 32 & a_in [31:0] $end
   $var wire 32 ' b_in [31:0] $end
   $var wire 32 ( c_in [31:0] $end
   $var wire 32 ) c_out [31:0] $end
  $upscope $end
 $upscope $end
$enddefinitions $end


#0
0#
0$
0%
b00000000000000000000000000000000 &
b00000000000000000000000000000000 '
b00000000000000000000000000000000 (
b00000000000000000000000000000000 )
b00000000000000000000000000001000 *
b00000000000000000000000000000100 +
#1
1#
1$
#2
0#
#3
1#
0$
1%
b00000010000000110000001100000010 &
#4
0#
#5
1#
b00000011000000100000000100000001 &
#6
0#
#7
1#
b00000000000000100000001100000001 &
#8
0#
#9
1#
b00000011000000010000001000000011 &
#10
0#
#11
1#
0%
b00000000000000000000000000000000 &
b00000011000000100000001100000000 '
#12
0#
#13
1#
b00000011000000100000000000000010 '
#14
0#
#15
1#
b00000001000000100000001100000000 '
b00010101000100000000110100010001 )
#16
0#
#17
1#
b00000010000000110000000100000000 '
b00010000000011110000011000010001 )
#18
0#
#19
1#
b00000000000000000000000000000000 '
b00010001000010100000110100001011 )
#20
0#
#21
1#
b00010000000011010000100100001011 )
