hw/hw03-hwml/handout/PEArray2.sv
module PEArray2 #(
    parameter W = 8,
    parameter N = 4
)(
    input logic clk, rst, stationaryCtrl,
    input logic [N-1:0][W-1:0] a_in,
    input logic [N-1:0][W-1:0] b_in,
    input logic [N-1:0][W-1:0] c_in,
    output logic [N-1:0][W-1:0] c_out
);
    assign c_out = c_in;
endmodule

hw/hw03-hwml/handout/gold-wave/VPEArray2.8x8x8.0.vcd
$version Generated by VerilatedVcd $end
$timescale 1ps $end
 $scope module TOP $end
  $var wire 1 # clk $end
  $var wire 1 $ rst $end
  $var wire 1 % stationaryCtrl $end
  $var wire 32 & a_in [31:0] $end
  $var wire 32 ' b_in [31:0] $end
  $var wire 32 ( c_in [31:0] $end
  $var wire 32 ) c_out [31:0] $end
  $scope module PEArray2 $end
   $var wire 32 * W [31:0] $end
   $var wire 32 + N [31:0] $end
   $var wire 1 # clk $end
   $var wire 1 $ rst $end
   $var wire 1 % stationaryCtrl $end
   $var wire 32 & a_in [31:0] $end
   $var wire 32 ' b_in [31:0] $end
   $var wire 32 ( c_in [31:0] $end
   $var wire 32 ) c_out [31:0] $end
  $upscope $end
 $upscope $end
$enddefinitions $end


#0
0#
0$
0%
b00000000000000000000000000000000 &
b00000000000000000000000000000000 '
b00000000000000000000000000000000 (
b00000000000000000000000000000000 )
b00000000000000000000000000001000 *
b00000000000000000000000000000100 +
#1
1#
1$
#2
0#
#3
1#
0$
1%
b00000001000000100000001100000000 &
#4
0#
#5
1#
b00000000000000100000001100000011 &
#6
0#
#7
1#
b00000000000000110000001100000010 &
#8
0#
#9
1#
b00000000000000110000001100000001 &
#10
0#
#11
1#
0%
b00000000000000000000000000000000 &
b00000000000000000000000000000011 '
#12
0#
#13
1#
b00000011000000100000000000000001 '
#14
0#
#15
1#
b00000010000000000000001100000010 '
b00000000000010010000011000000011 )
#16
0#
#17
1#
b00000011000000000000001100000000 '
b00000111000001110000100000000111 )
#18
0#
#19
1#
b00000010000000010000000100000011 '
b00001011000011110000110100001011 )
#20
0#
#21
1#
b00000011000000010000001000000011 '
b00001100000010010000100100001001 )
#22
0#
#23
1#
b00000000000000010000001000000000 '
b00000111000011100000110000001001 )
#24
0#
#25
1#
b00000001000000000000000000000001 '
b00001011000100010000111100001100 )
#26
0#
#27
1#
b00000000000000000000000000000000 '
b00001000000010000000100100001001 )
#28
0#
#29
1#
b00000001000000110000001000000001 )
#30
0#
#31
1#
1%
b00000011000000010000001100000010 &
b00000000000000000000000000000000 )
#32
0#
#33
1#
b00000001000000000000001100000000 &
#34
0#
#35
1#
#36
0#
#37
1#
b00000001000000100000000100000001 &
#38
0#
#39
1#
0%
b00000000000000000000000000000000 &
b00000011000000100000001000000000 '
b00000000000010010000011000000011 (
b00000000000010010000011000000011 )
#40
0#
#41
1#
b00000010000000000000000000000010 '
b00000111000001110000100000000111 (
b00000111000001110000100000000111 )
#42
0#
#43
1#
b00000001000000110000000100000001 '
b00001011000011110000110100001011 (
b00011100000110000001011000010100 )
#44
0#
#45
1#
b00000001000000110000001100000011 '
b00001100000010010000100100001001 (
b00010110000010110000101100001101 )
#46
0#
#47
1#
b00000001000000100000001100000010 '
b00000111000011100000110000001001 (
b00010010000100100001000000010010 )
#48
0#
#49
1#
b00000010000000000000000000000010 '
b00001011000100010000111100001100 (
b00100000000110110001100100011001 )
#50
0#
#51
1#
b00000010000000000000000000000001 '
b00001000000010000000100100001001 (
b00011010000100100001001100010011 )
#52
0#
#53
1#
b00000001000000100000001100000010 '
b00000000000000000000000000000000 (
b00001010000000100000001000000100 )
#54
0#
#55
1#
b00000000000000000000000000000000 '
b00001000000000100000001000000011 )
#56
0#
#57
1#
b00010010000010100000101000001010 )
#58
0#
#59
1#
1%
b00000001000000100000001100000011 &
b00000000000000000000000000000000 )
#60
0#
#61
1#
b00000000000000110000000100000011 &
#62
0#
#63
1#
b00000010000000000000000000000010 &
#64
0#
#65
1#
b00000000000000000000000000000011 &
#66
0#
#67
1#
0%
b00000000000000000000000000000000 &
b00000000000000000000000000000011 '
#68
0#
#69
1#
b00000011000000100000000000000001 '
#70
0#
#71
1#
b00000010000000000000001100000010 '
b00001001000010010000011000001001 )
#72
0#
#73
1#
b00000011000000000000001100000000 '
b00001010000010010000100000000011 )
#74
0#
#75
1#
b00000010000000010000000100000011 '
b00010001000010010000100000000110 )
#76
0#
#77
1#
b00000011000000010000001000000011 '
b00001100000000110000011000000000 )
#78
0#
#79
1#
b00000000000000010000001000000000 '
b00010000000011010000101000001001 )
#80
0#
#81
1#
b00000001000000000000000000000001 '
b00010100000011100000110000001001 )
#82
0#
#83
1#
b00000000000000000000000000000000 '
b00001000000001010000000000000000 )
#84
0#
#85
1#
b00000100000000110000010000000011 )
#86
0#
#87
1#
1%
b00000001000000010000001100000010 &
b00000000000000000000000000000000 )
#88
0#
#89
1#
b00000000000000010000001100000000 &
#90
0#
#91
1#
b00000011000000110000000000000011 &
#92
0#
#93
1#
b00000000000000010000001000000001 &
#94
0#
#95
1#
0%
b00000000000000000000000000000000 &
b00000011000000100000001000000000 '
b00001001000010010000011000001001 (
b00001001000010010000011000001001 )
#96
0#
#97
1#
b00000010000000000000000000000010 '
b00001010000010010000100000000011 (
b00001010000010010000100000000011 )
#98
0#
#99
1#
b00000001000000110000000100000001 '
b00010001000010010000100000000110 (
b00011100000100010001011100001100 )
#100
0#
#101
1#
b00000001000000110000001100000011 '
b00001100000000110000011000000000 (
b00010010000000110001001000000010 )
#102
0#
#103
1#
b00000001000000100000001100000010 '
b00010000000011010000101000001001 (
b00011001000100110001100100001111 )
#104
0#
#105
1#
b00000010000000000000000000000010 '
b00010100000011100000110000001001 (
b00100111000110100010000100010101 )
#106
0#
#107
1#
b00000010000000000000000000000001 '
b00001000000001010000000000000000 (
b00011000000100000000111100001010 )
#108
0#
#109
1#
b00000001000000100000001100000010 '
b00000000000000000000000000000000 (
b00000110000000000000110000000010 )
#110
0#
#111
1#
b00000000000000000000000000000000 '
b00000100000000000000100100000001 )
#112
0#
#113
1#
b00010000000010110000111100001010 )
