hw/hw03-hwml/handout/PEArray1.sv
module PEArray1 #(
    parameter W = 8,
    parameter N = 4
)(
    input logic clk, rst, stationaryCtrl,
    input logic [N-1:0][W-1:0] a_in,
    input logic [N-1:0][W-1:0] b_in,
    input logic [N-1:0][W-1:0] c_in,
    output logic [N-1:0][W-1:0] c_out
);
    assign c_out = c_in;
endmodule

hw/hw03-hwml/handout/gold-wave/VPEArray1.9x16x16.0.vcd
$version Generated by VerilatedVcd $end
$timescale 1ps $end
 $scope module TOP $end
  $var wire 1 # clk $end
  $var wire 1 $ rst $end
  $var wire 1 % stationaryCtrl $end
  $var wire 32 & a_in [31:0] $end
  $var wire 32 ' b_in [31:0] $end
  $var wire 32 ( c_in [31:0] $end
  $var wire 32 ) c_out [31:0] $end
  $scope module PEArray1 $end
   $var wire 32 * W [31:0] $end
   $var wire 32 + N [31:0] $end
   $var wire 1 # clk $end
   $var wire 1 $ rst $end
   $var wire 1 % stationaryCtrl $end
   $var wire 32 & a_in [31:0] $end
   $var wire 32 ' b_in [31:0] $end
   $var wire 32 ( c_in [31:0] $end
   $var wire 32 ) c_out [31:0] $end
  $upscope $end
 $upscope $end
$enddefinitions $end


#0
0#
0$
0%
b00000000000000000000000000000000 &
b00000000000000000000000000000000 '
b00000000000000000000000000000000 (
b00000000000000000000000000000000 )
b00000000000000000000000000001000 *
b00000000000000000000000000000100 +
#1
1#
1$
#2
0#
#3
1#
0$
1%
b00000000000000000000000100000000 '
#4
0#
#5
1#
b00000001000000000000001100000001 '
#6
0#
#7
1#
b00000000000000100000001100000000 '
#8
0#
#9
1#
b00000011000000100000000100000001 '
#10
0#
#11
1#
0%
b00000000000000000000000000000000 '
#12
0#
#13
1#
b00000000000000000000001000000000 &
#14
0#
#15
1#
b00000000000000000000001000000010 &
#16
0#
#17
1#
b00000000000000010000000000000000 &
#18
0#
#19
1#
b00000011000000110000000000000000 &
#20
0#
#21
1#
b00000011000000000000001100000011 &
b00000000000000000000011000000001 )
#22
0#
#23
1#
b00000010000000110000000000000000 &
b00000000000001000000110000000101 )
#24
0#
#25
1#
b00000010000000110000001100000010 &
b00000000000001000000111000000000 )
#26
0#
#27
1#
b00000001000000010000000100000011 &
b00000001000001000000001000000011 )
#28
0#
#29
1#
b00000000000000010000001000000000 &
b00001001000000000001010000000110 )
#30
0#
#31
1#
b00000000000000000000000000000000 &
b00000000000001100000110100000001 )
#32
0#
#33
1#
b00000010000000000000000000000000 &
b00000011000001100000110000000011 )
#34
0#
#35
1#
b00000000000000000000000000000000 &
b00001100000001100000100000000011 )
#36
0#
#37
1#
b00000001000001100000101100000000 )
#38
0#
#39
1#
b00000111000010100000000000000000 )
#40
0#
#41
1#
b00001001000000000000000000000000 )
#42
0#
#43
1#
1%
b00000010000000110000001100000011 '
b00000000000000000000000000000000 )
#44
0#
#45
1#
b00000010000000000000000000000010 '
#46
0#
#47
1#
b00000000000000000000000100000010 '
#48
0#
#49
1#
b00000001000000000000001000000011 '
#50
0#
#51
1#
0%
b00000000000000000000000000000001 &
b00000000000000000000000000000000 '
#52
0#
#53
1#
b00000000000000000000000100000010 &
b00000000000000000000011000000001 (
#54
0#
#55
1#
b00000000000000010000001000000010 &
b00000000000001000000110000000101 (
#56
0#
#57
1#
b00000000000000010000000000000010 &
b00000000000001000000111000000000 (
#58
0#
#59
1#
b00000010000000000000000100000000 &
b00000001000001000000001000000011 (
b00000000000000000000011000001000 )
#60
0#
#61
1#
b00000010000000000000001100000001 &
b00001001000000000001010000000110 (
b00000000000001000000111100010111 )
#62
0#
#63
1#
b00000000000000010000000000000011 &
b00000000000001100000110100000001 (
b00000000000001000001101000001100 )
#64
0#
#65
1#
b00000011000000100000001000000001 &
b00000011000001100000110000000011 (
b00000100000010100000110000001011 )
#66
0#
#67
1#
b00000011000000110000001100000000 &
b00001100000001100000100000000011 (
b00010001000001100001100100010111 )
#68
0#
#69
1#
b00000000000000110000000000000000 &
b00000001000001100000101100000000 (
b00000110000001100001100100010001 )
#70
0#
#71
1#
b00000011000000100000000000000000 &
b00000111000010100000000000000000 (
b00000101000011110001011100010110 )
#72
0#
#73
1#
b00000001000000000000000000000000 &
b00000000000000000000000000000000 (
b00010100000011110001000000011011 )
#74
0#
#75
1#
b00000000000000000000000000000000 &
b00001100000001100001100100000111 )
#76
0#
#77
1#
b00010000000100110000001100000000 )
#78
0#
#79
1#
b00001101000000110000000000000000 )
#80
0#
#81
1#
b00000110000000000000000000000000 )
#82
0#
#83
1#
1%
b00000001000000100000000000000000 '
b00000000000000000000000000000000 )
#84
0#
#85
1#
b00000010000000100000001000000001 '
#86
0#
#87
1#
b00000000000000100000000100000001 '
#88
0#
#89
1#
b00000011000000100000000000000001 '
#90
0#
#91
1#
0%
b00000000000000000000000000000000 '
b00000000000000000000000000001000 (
#92
0#
#93
1#
b00000000000000000000001100000010 &
b00000000000000000000111100010111 (
#94
0#
#95
1#
b00000000000000100000000000000011 &
b00000000000001000001101000001100 (
#96
0#
#97
1#
b00000011000000010000001000000010 &
b00000100000010100000110000001011 (
b00000000000000000000000000001000 )
#98
0#
#99
1#
b00000011000000010000001000000001 &
b00010001000001100001100100010111 (
b00000000000000000000111100011100 )
#100
0#
#101
1#
b00000001000000000000001000000010 &
b00000110000001100001100100010001 (
b00000000000001000010000100001111 )
#102
0#
#103
1#
b00000001000000010000001000000000 &
b00000101000011110001011100010110 (
b00000100000110100000111000010001 )
#104
0#
#105
1#
b00000010000000000000000000000001 &
b00010100000011110001000000011011 (
b00011000000100100001110100011011 )
#106
0#
#107
1#
b00000000000000110000000000000000 &
b00001100000001100001100100000111 (
b00010001000101000001101100010101 )
#108
0#
#109
1#
b00000001000000110000000100000000 &
b00010000000100110000001100000000 (
b00010001000110010001101100011010 )
#110
0#
#111
1#
b00000011000000100000000000000000 &
b00001101000000110000000000000000 (
b00011011000110110001001000011110 )
#112
0#
#113
1#
b00000000000000000000000000000000 &
b00000000000000000000000000000000 (
b00010011000011100001111100001011 )
#114
0#
#115
1#
b00010110000110110000100100000011 )
#116
0#
#117
1#
b00010100000100010000010100000000 )
#118
0#
#119
1#
b00001100000001100000000000000000 )
#120
0#
#121
1#
b00000100000000000000000000000000 )
#122
0#
#123
1#
1%
b00000001000000100000000000000001 '
b00000000000000000000000000000000 )
#124
0#
#125
1#
b00000001000000010000001000000001 '
#126
0#
#127
1#
b00000000000000100000001000000010 '
#128
0#
#129
1#
b00000010000000000000001100000010 '
#130
0#
#131
1#
0%
b00000000000000000000000000000010 &
b00000000000000000000000000000000 '
b00000000000000000000000000011100 (
#132
0#
#133
1#
b00000000000000000000001100000011 &
b00000000000000000010000100001111 (
#134
0#
#135
1#
b00000000000000000000000000000001 &
b00000000000110100000111000010001 (
#136
0#
#137
1#
b00000001000000000000001000000010 &
b00011000000100100001110100011011 (
b00000000000000000000000000011100 )
#138
0#
#139
1#
b00000011000000100000000000000000 &
b00010001000101000001101100010101 (
b00000000000000000010000100011010 )
#140
0#
#141
1#
b00000001000000000000001100000010 &
b00010001000110010001101100011010 (
b00000000000110100001101000011010 )
#142
0#
#143
1#
b00000000000000110000000000000000 &
b00011011000110110001001000011110 (
b00011000000110100010011000100100 )
#144
0#
#145
1#
b00000001000000000000001000000000 &
b00010011000011100001111100001011 (
b00010110000110100010011000011001 )
#146
0#
#147
1#
b00000010000000100000001100000000 &
b00010110000110110000100100000011 (
b00011010001000010010000100100100 )
#148
0#
#149
1#
b00000011000000010000000000000000 &
b00010100000100010000010100000000 (
b00100000000110110001111000100100 )
#150
0#
#151
1#
b00000000000000000000000000000000 &
b00001100000001100000000000000000 (
b00010111000110010010010100010100 )
#152
0#
#153
1#
b00000010000000000000000000000000 &
b00000000000000000000000000000000 (
b00011010000111110001000100001010 )
#154
0#
#155
1#
b00000000000000000000000000000000 &
b00011010000111010000110100000010 )
#156
0#
#157
1#
b00010001000011010000000000000000 )
#158
0#
#159
1#
b00000001000001000000000000000000 )
#160
0#
#161
1#
b00000010000000000000000000000000 )
#162
0#
#163
1#
1%
b00000000000000000000001000000010 '
b00000000000000000000000000000000 )
#164
0#
#165
1#
b00000011000000100000001000000001 '
#166
0#
#167
1#
b00000000000000010000000100000011 '
#168
0#
#169
1#
b00000001000000100000001000000000 '
#170
0#
#171
1#
0%
b00000000000000000000000000000000 '
#172
0#
#173
1#
b00000000000000000000001000000000 &
#174
0#
#175
1#
b00000000000000000000001000000010 &
#176
0#
#177
1#
b00000000000000010000000000000000 &
#178
0#
#179
1#
b00000011000000110000000000000000 &
b00000000000000000000000000000110 )
#180
0#
#181
1#
b00000011000000000000001100000011 &
b00000000000000000000001000001101 )
#182
0#
#183
1#
b00000010000000110000000000000000 &
b00000000000000100000101000001001 )
#184
0#
#185
1#
b00000010000000110000001100000010 &
b00000000000001000001000000000100 )
#186
0#
#187
1#
b00000001000000010000000100000011 &
b00000011000010100000010000010000 )
#188
0#
#189
1#
b00000000000000010000001000000000 &
b00001011000000000000110100000101 )
#190
0#
#191
1#
b00000000000000000000000000000000 &
b00000000000010010000111000001010 )
#192
0#
#193
1#
b00000010000000000000000000000000 &
b00001001000011000000010100000100 )
#194
0#
#195
1#
b00000000000000000000000000000000 &
b00001100000001010000011100001010 )
#196
0#
#197
1#
b00000011000001110000110000000000 )
#198
0#
#199
1#
b00000101000010000000000000000000 )
#200
0#
#201
1#
b00000011000000000000000000000000 )
#202
0#
#203
1#
1%
b00000011000000110000000000000011 '
b00000000000000000000000000000000 )
#204
0#
#205
1#
b00000011000000110000000100000010 '
#206
0#
#207
1#
b00000001000000010000000000000011 '
#208
0#
#209
1#
b00000001000000000000001000000000 '
#210
0#
#211
1#
0%
b00000000000000000000000000000001 &
b00000000000000000000000000000000 '
b00000000000000000000000000000110 (
#212
0#
#213
1#
b00000000000000000000000100000010 &
b00000000000000000000001000001101 (
#214
0#
#215
1#
b00000000000000010000001000000010 &
b00000000000000100000101000001001 (
#216
0#
#217
1#
b00000000000000010000000000000010 &
b00000000000001000001000000000100 (
b00000000000000000000000000000110 )
#218
0#
#219
1#
b00000010000000000000000100000000 &
b00000011000010100000010000010000 (
b00000000000000000000001000010010 )
#220
0#
#221
1#
b00000010000000000000001100000001 &
b00001011000000000000110100000101 (
b00000000000000100000110100010111 )
#222
0#
#223
1#
b00000000000000010000000000000011 &
b00000000000010010000111000001010 (
b00000000000010000001010100001010 )
#224
0#
#225
1#
b00000011000000100000001000000001 &
b00001001000011000000010100000100 (
b00001000000101010000100000010011 )
#226
0#
#227
1#
b00000011000000110000001100000000 &
b00001100000001010000011100001010 (
b00011000000001100001000100011001 )
#228
0#
#229
1#
b00000000000000110000000000000000 &
b00000011000001110000110000000000 (
b00001000000010100000111100010111 )
#230
0#
#231
1#
b00000011000000100000000000000000 &
b00000101000010000000000000000000 (
b00001100000110110000100100010000 )
#232
0#
#233
1#
b00000001000000000000000000000000 &
b00000000000000000000000000000000 (
b00011011000101000001000000100010 )
#234
0#
#235
1#
b00000000000000000000000000000000 &
b00010011000100100001000100000111 )
#236
0#
#237
1#
b00010011000111010000001000000000 )
#238
0#
#239
1#
b00010110000010010000000000000000 )
#240
0#
#241
1#
b00001001000000000000000000000000 )
#242
0#
#243
1#
1%
b00000010000000110000001000000010 '
b00000000000000000000000000000000 )
#244
0#
#245
1#
b00000000000000100000000100000000 '
#246
0#
#247
1#
b00000001000000000000001000000001 '
#248
0#
#249
1#
b00000000000000110000000100000001 '
#250
0#
#251
1#
0%
b00000000000000000000000000000000 '
b00000000000000000000000000010010 (
#252
0#
#253
1#
b00000000000000000000001100000010 &
b00000000000000000000110100010111 (
#254
0#
#255
1#
b00000000000000100000000000000011 &
b00000000000010000001010100001010 (
#256
0#
#257
1#
b00000011000000010000001000000010 &
b00001000000101010000100000010011 (
b00000000000000000000000000010010 )
#258
0#
#259
1#
b00000011000000010000001000000001 &
b00011000000001100001000100011001 (
b00000000000000000000110100100000 )
#260
0#
#261
1#
b00000001000000000000001000000010 &
b00001000000010100000111100010111 (
b00000000000010000010001100010010 )
#262
0#
#263
1#
b00000001000000010000001000000000 &
b00001100000110110000100100010000 (
b00001000001000100001000100011010 )
#264
0#
#265
1#
b00000010000000000000000000000001 &
b00011011000101000001000000100010 (
b00100001000101110001101100011111 )
#266
0#
#267
1#
b00000000000000110000000000000000 &
b00010011000100100001000100000111 (
b00001110000110000001011100011110 )
#268
0#
#269
1#
b00000001000000110000000100000000 &
b00010011000111010000001000000000 (
b00010000001001000001001100010100 )
#270
0#
#271
1#
b00000011000000100000000000000000 &
b00010110000010010000000000000000 (
b00011111000111110001011000100100 )
#272
0#
#273
1#
b00000000000000000000000000000000 &
b00000000000000000000000000000000 (
b00011001000110000001011000001110 )
#274
0#
#275
1#
b00010101001001100000110000000001 )
#276
0#
#277
1#
b00011000000110110000010000000000 )
#278
0#
#279
1#
b00000110000001000000000000000000 )
#280
0#
#281
1#
b00000001000000000000000000000000 )
#282
0#
#283
1#
1%
b00000010000000010000000100000001 '
b00000000000000000000000000000000 )
#284
0#
#285
1#
b00000010000000110000001100000001 '
#286
0#
#287
1#
b00000000000000100000000100000000 '
#288
0#
#289
1#
b00000001000000100000001100000000 '
#290
0#
#291
1#
0%
b00000000000000000000000000000010 &
b00000000000000000000000000000000 '
b00000000000000000000000000100000 (
#292
0#
#293
1#
b00000000000000000000001100000011 &
b00000000000000000010001100010010 (
#294
0#
#295
1#
b00000000000000000000000000000001 &
b00000000001000100001000100011010 (
#296
0#
#297
1#
b00000001000000000000001000000010 &
b00100001000101110001101100011111 (
b00000000000000000000000000100000 )
#298
0#
#299
1#
b00000011000000100000000000000000 &
b00001110000110000001011100011110 (
b00000000000000000010001100010011 )
#300
0#
#301
1#
b00000001000000000000001100000010 &
b00010000001001000001001100010100 (
b00000000001000100001101100011101 )
#302
0#
#303
1#
b00000000000000110000000000000000 &
b00011111000111110001011000100100 (
b00100001001000100010011100100010 )
#304
0#
#305
1#
b00000001000000000000001000000000 &
b00011001000110000001011000001110 (
b00010010001000010010001100011110 )
#306
0#
#307
1#
b00000010000000100000001100000000 &
b00010101001001100000110000000001 (
b00011001001100010001100100011000 )
#308
0#
#309
1#
b00000011000000010000000000000000 &
b00011000000110110000010000000000 (
b00100110001000110010001100100110 )
#310
0#
#311
1#
b00000000000000000000000000000000 &
b00000110000001000000000000000000 (
b00011011001010000001111000010011 )
#312
0#
#313
1#
b00000010000000000000000000000000 &
b00000000000000000000000000000000 (
b00011101001011000001011100000010 )
#314
0#
#315
1#
b00000000000000000000000000000000 &
b00011110001010000000101000000010 )
#316
0#
#317
1#
b00010000000011010000001000000000 )
#318
0#
#319
1#
b00000010000000100000000000000000 )
#320
0#
#321
1#
b00000100000000000000000000000000 )
#322
0#
#323
1#
1%
b00000001000000110000000000000001 '
b00000000000000000000000000000000 )
#324
0#
#325
1#
b00000010000000100000001000000000 '
#326
0#
#327
1#
b00000010000000000000001100000010 '
#328
0#
#329
1#
b00000010000000000000001000000010 '
#330
0#
#331
1#
0%
b00000000000000000000000000000000 '
#332
0#
#333
1#
b00000000000000000000001000000000 &
#334
0#
#335
1#
b00000000000000000000001000000010 &
#336
0#
#337
1#
b00000000000000010000000000000000 &
#338
0#
#339
1#
b00000011000000110000000000000000 &
b00000000000000000000000000000100 )
#340
0#
#341
1#
b00000011000000000000001100000011 &
b00000000000000000000011000000111 )
#342
0#
#343
1#
b00000010000000110000000000000000 &
b00000000000000000000100000000111 )
#344
0#
#345
1#
b00000010000000110000001100000010 &
b00000100000010110000101000000010 )
#346
0#
#347
1#
b00000001000000010000000100000011 &
b00001001000011110000000000001000 )
#348
0#
#349
1#
b00000000000000010000001000000000 &
b00001101000001100000111100000111 )
#350
0#
#351
1#
b00000000000000000000000000000000 &
b00000010000011000000110000000110 )
#352
0#
#353
1#
b00000010000000000000000000000000 &
b00001110000010010000101100000110 )
#354
0#
#355
1#
b00000000000000000000000000000000 &
b00001101000000100000100100001100 )
#356
0#
#357
1#
b00001000000000100000110000000000 )
#358
0#
#359
1#
b00001000000001100000000000000000 )
#360
0#
#361
1#
b00001100000000000000000000000000 )
#362
0#
#363
1#
1%
b00000000000000010000000100000000 '
b00000000000000000000000000000000 )
#364
0#
#365
1#
b00000011000000000000001000000011 '
#366
0#
#367
1#
b00000001000000100000000000000000 '
#368
0#
#369
1#
b00000001000000110000001000000001 '
#370
0#
#371
1#
0%
b00000000000000000000000000000001 &
b00000000000000000000000000000000 '
b00000000000000000000000000000100 (
#372
0#
#373
1#
b00000000000000000000000100000010 &
b00000000000000000000011000000111 (
#374
0#
#375
1#
b00000000000000010000001000000010 &
b00000000000000000000100000000111 (
#376
0#
#377
1#
b00000000000000010000000000000010 &
b00000100000010110000101000000010 (
b00000000000000000000000000000100 )
#378
0#
#379
1#
b00000010000000000000000100000000 &
b00001001000011110000000000001000 (
b00000000000000000000011000001011 )
#380
0#
#381
1#
b00000010000000000000001100000001 &
b00001101000001100000111100000111 (
b00000000000000000000110000001100 )
#382
0#
#383
1#
b00000000000000010000000000000011 &
b00000010000011000000110000000110 (
b00000100000100000001001000000100 )
#384
0#
#385
1#
b00000011000000100000001000000001 &
b00001110000010010000101100000110 (
b00001110000110110000011000001010 )
#386
0#
#387
1#
b00000011000000110000001100000000 &
b00001101000000100000100100001100 (
b00010100000011100001001100001010 )
#388
0#
#389
1#
b00000000000000110000000000000000 &
b00001000000000100000110000000000 (
b00000100000101000001000100001101 )
#390
0#
#391
1#
b00000011000000100000000000000000 &
b00001000000001100000000000000000 (
b00010001000100100001010000010010 )
#392
0#
#393
1#
b00000001000000000000000000000000 &
b00000000000000000000000000000000 (
b00010011000010000001010100010110 )
#394
0#
#395
1#
b00000000000000000000000000000000 &
b00001111000011110001011100000110 )
#396
0#
#397
1#
b00010110000100100000010100000000 )
#398
0#
#399
1#
b00001101000000010000000000000000 )
#400
0#
#401
1#
b00000110000000000000000000000000 )
#402
0#
#403
1#
1%
b00000001000000110000000000000011 '
b00000000000000000000000000000000 )
#404
0#
#405
1#
b00000010000000000000001000000001 '
#406
0#
#407
1#
b00000001000000010000000100000011 '
#408
0#
#409
1#
b00000000000000110000001100000000 '
#410
0#
#411
1#
0%
b00000000000000000000000000000000 '
b00000000000000000000000000001011 (
#412
0#
#413
1#
b00000000000000000000001100000010 &
b00000000000000000000110000001100 (
#414
0#
#415
1#
b00000000000000100000000000000011 &
b00000000000100000001001000000100 (
#416
0#
#417
1#
b00000011000000010000001000000010 &
b00001110000110110000011000001010 (
b00000000000000000000000000001011 )
#418
0#
#419
1#
b00000011000000010000001000000001 &
b00010100000011100001001100001010 (
b00000000000000000000110000100000 )
#420
0#
#421
1#
b00000001000000000000001000000010 &
b00000100000101000001000100001101 (
b00000000000100000001100100001110 )
#422
0#
#423
1#
b00000001000000010000001000000000 &
b00010001000100100001010000010010 (
b00001110001001110000111000010100 )
#424
0#
#425
1#
b00000010000000000000000000000001 &
b00010011000010000001010100010110 (
b00011110000111010010000000010011 )
#426
0#
#427
1#
b00000000000000110000000000000000 &
b00001111000011110001011100000110 (
b00001001001000100001100100011010 )
#428
0#
#429
1#
b00000001000000110000000100000000 &
b00010110000100100000010100000000 (
b00010110000111010001101100011000 )
#430
0#
#431
1#
b00000011000000100000000000000000 &
b00001101000000010000000000000000 (
b00010110000100110001110100011100 )
#432
0#
#433
1#
b00000000000000000000000000000000 &
b00000000000000000000000000000000 (
b00010101000101110001110100010010 )
#434
0#
#435
1#
b00011000000101010000111000000101 )
#436
0#
#437
1#
b00010100000011010000010100000000 )
#438
0#
#439
1#
b00001001000000010000000000000000 )
#440
0#
#441
1#
b00000101000000000000000000000000 )
#442
0#
#443
1#
1%
b00000011000000010000001100000010 '
b00000000000000000000000000000000 )
#444
0#
#445
1#
b00000001000000110000001000000001 '
#446
0#
#447
1#
b00000011000000010000000100000001 '
#448
0#
#449
1#
b00000001000000110000001000000001 '
#450
0#
#451
1#
0%
b00000000000000000000000000000010 &
b00000000000000000000000000000000 '
b00000000000000000000000000100000 (
#452
0#
#453
1#
b00000000000000000000001100000011 &
b00000000000000000001100100001110 (
#454
0#
#455
1#
b00000000000000000000000000000001 &
b00000000001001110000111000010100 (
#456
0#
#457
1#
b00000001000000000000001000000010 &
b00011110000111010010000000010011 (
b00000000000000000000000000100000 )
#458
0#
#459
1#
b00000011000000100000000000000000 &
b00001001001000100001100100011010 (
b00000000000000000001100100010101 )
#460
0#
#461
1#
b00000001000000000000001100000010 &
b00010110000111010001101100011000 (
b00000000001001110001100000011101 )
#462
0#
#463
1#
b00000000000000110000000000000000 &
b00010110000100110001110100011100 (
b00011110001001110010111100011010 )
#464
0#
#465
1#
b00000001000000000000001000000000 &
b00010101000101110001110100010010 (
b00010111001011100010010000011100 )
#466
0#
#467
1#
b00000010000000100000001100000000 &
b00011000000101010000111000000101 (
b00100010001010010001111100100000 )
#468
0#
#469
1#
b00000011000000010000000000000000 &
b00010100000011010000010100000000 (
b00100010000110010010100100100010 )
#470
0#
#471
1#
b00000000000000000000000000000000 &
b00001001000000010000000000000000 (
b00010111001001000010011100011100 )
#472
0#
#473
1#
b00000010000000000000000000000000 &
b00000000000000000000000000000000 (
b00100111000111010001110100001001 )
#474
0#
#475
1#
b00000000000000000000000000000000 &
b00011100000110000000101000000100 )
#476
0#
#477
1#
b00011010000001110000011000000000 )
#478
0#
#479
1#
b00001010000000100000000000000000 )
#480
0#
#481
1#
b00000110000000000000000000000000 )
#482
0#
#483
1#
1%
b00000010000000100000000000000001 '
b00000000000000000000000000000000 )
#484
0#
#485
1#
b00000000000000100000000100000000 '
#486
0#
#487
1#
b00000001000000010000000000000011 '
#488
0#
#489
1#
b00000000000000110000000100000001 '
#490
0#
#491
1#
0%
b00000000000000000000000000000000 '
#492
0#
#493
1#
b00000000000000000000001000000000 &
#494
0#
#495
1#
b00000000000000000000001000000010 &
#496
0#
#497
1#
b00000000000000010000000000000000 &
#498
0#
#499
1#
b00000011000000110000000000000000 &
b00000000000000000000000000000110 )
#500
0#
#501
1#
b00000011000000000000001100000011 &
b00000000000000000000000000001001 )
#502
0#
#503
1#
b00000010000000110000000000000000 &
b00000000000000100000000100000101 )
#504
0#
#505
1#
b00000010000000110000001100000010 &
b00000010000010100000010100000010 )
#506
0#
#507
1#
b00000001000000010000000100000011 &
b00001000000100100000000000001011 )
#508
0#
#509
1#
b00000000000000010000001000000000 &
b00000110000001000000001100000100 )
#510
0#
#511
1#
b00000000000000000000000000000000 &
b00000100000011010000011000001001 )
#512
0#
#513
1#
b00000010000000000000000000000000 &
b00000111000100010000000100000101 )
#514
0#
#515
1#
b00000000000000000000000000000000 &
b00000010000001010000001100001011 )
#516
0#
#517
1#
b00000011000010010000001100000000 )
#518
0#
#519
1#
b00000001000011110000000000000000 )
#520
0#
#521
1#
b00000110000000000000000000000000 )
#522
0#
#523
1#
1%
b00000011000000110000000100000001 '
b00000000000000000000000000000000 )
#524
0#
#525
1#
b00000010000000110000000100000000 '
#526
0#
#527
1#
b00000011000000000000000000000000 '
#528
0#
#529
1#
b00000000000000010000000100000011 '
#530
0#
#531
1#
0%
b00000000000000000000000000000001 &
b00000000000000000000000000000000 '
b00000000000000000000000000000110 (
#532
0#
#533
1#
b00000000000000000000000100000010 &
b00000000000000000000000000001001 (
#534
0#
#535
1#
b00000000000000010000001000000010 &
b00000000000000100000000100000101 (
#536
0#
#537
1#
b00000000000000010000000000000010 &
b00000010000010100000010100000010 (
b00000000000000000000000000000110 )
#538
0#
#539
1#
b00000010000000000000000100000000 &
b00001000000100100000000000001011 (
b00000000000000000000000000001100 )
#540
0#
#541
1#
b00000010000000000000001100000001 &
b00000110000001000000001100000100 (
b00000000000000100000001100001101 )
#542
0#
#543
1#
b00000000000000010000000000000011 &
b00000100000011010000011000001001 (
b00000010000011100000101000001010 )
#544
0#
#545
1#
b00000011000000100000001000000001 &
b00000111000100010000000100000101 (
b00001101000111010000010000010001 )
#546
0#
#547
1#
b00000011000000110000001100000000 &
b00000010000001010000001100001011 (
b00010100000011000000010100000111 )
#548
0#
#549
1#
b00000000000000110000000000000000 &
b00000011000010010000001100000000 (
b00001010000011110000101000001111 )
#550
0#
#551
1#
b00000011000000100000000000000000 &
b00000001000011110000000000000000 (
b00001010000111010000011100001110 )
#552
0#
#553
1#
b00000001000000000000000000000000 &
b00000000000000000000000000000000 (
b00010110000101010000100100010001 )
#554
0#
#555
1#
b00000000000000000000000000000000 &
b00010000000101010000101000000001 )
#556
0#
#557
1#
b00001101001000100000001100000000 )
#558
0#
#559
1#
b00011000000010010000000000000000 )
#560
0#
#561
1#
b00000111000000000000000000000000 )
#562
0#
#563
1#
1%
b00000010000000000000001100000001 '
b00000000000000000000000000000000 )
#564
0#
#565
1#
b00000010000000100000001000000000 '
#566
0#
#567
1#
b00000011000000000000000100000010 '
#568
0#
#569
1#
b00000000000000100000001000000001 '
#570
0#
#571
1#
0%
b00000000000000000000000000000000 '
b00000000000000000000000000001100 (
#572
0#
#573
1#
b00000000000000000000001100000010 &
b00000000000000000000001100001101 (
#574
0#
#575
1#
b00000000000000100000000000000011 &
b00000000000011100000101000001010 (
#576
0#
#577
1#
b00000011000000010000001000000010 &
b00001101000111010000010000010001 (
b00000000000000000000000000001100 )
#578
0#
#579
1#
b00000011000000010000001000000001 &
b00010100000011000000010100000111 (
b00000000000000000000001100010110 )
#580
0#
#581
1#
b00000001000000000000001000000010 &
b00001010000011110000101000001111 (
b00000000000011100001101000001111 )
#582
0#
#583
1#
b00000001000000010000001000000000 &
b00001010000111010000011100001110 (
b00001101001000010001001100011001 )
#584
0#
#585
1#
b00000010000000000000000000000001 &
b00010110000101010000100100010001 (
b00100111000100100001001000001110 )
#586
0#
#587
1#
b00000000000000110000000000000000 &
b00010000000101010000101000000001 (
b00010010000101110001001100010110 )
#588
0#
#589
1#
b00000001000000110000000100000000 &
b00001101001000100000001100000000 (
b00010100001000010001001100010100 )
#590
0#
#591
1#
b00000011000000100000000000000000 &
b00011000000010010000000000000000 (
b00011110000110010000111100010010 )
#592
0#
#593
1#
b00000000000000000000000000000000 &
b00000000000000000000000000000000 (
b00011100000110010001001100000101 )
#594
0#
#595
1#
b00010011001010000001010000000010 )
#596
0#
#597
1#
b00100000000100010000010100000000 )
#598
0#
#599
1#
b00001100000001000000000000000000 )
#600
0#
#601
1#
b00000111000000000000000000000000 )
#602
0#
#603
1#
1%
b00000010000000100000001100000001 '
b00000000000000000000000000000000 )
#604
0#
#605
1#
b00000010000000100000001100000000 '
#606
0#
#607
1#
b00000011000000010000001000000001 '
#608
0#
#609
1#
b00000000000000110000000100000000 '
#610
0#
#611
1#
0%
b00000000000000000000000000000010 &
b00000000000000000000000000000000 '
b00000000000000000000000000010110 (
#612
0#
#613
1#
b00000000000000000000001100000011 &
b00000000000000000001101000001111 (
#614
0#
#615
1#
b00000000000000000000000000000001 &
b00000000001000010001001100011001 (
#616
0#
#617
1#
b00000001000000000000001000000010 &
b00100111000100100001001000001110 (
b00000000000000000000000000010110 )
#618
0#
#619
1#
b00000011000000100000000000000000 &
b00010010000101110001001100010110 (
b00000000000000000001101000010011 )
#620
0#
#621
1#
b00000001000000000000001100000010 &
b00010100001000010001001100010100 (
b00000000001000010001111000011100 )
#622
0#
#623
1#
b00000000000000110000000000000000 &
b00011110000110010000111100010010 (
b00100111000111010001111000010001 )
#624
0#
#625
1#
b00000001000000000000001000000000 &
b00011100000110010001001100000101 (
b00011101001001100010000100010110 )
#626
0#
#627
1#
b00000010000000100000001100000000 &
b00010011001010000001010000000010 (
b00011010001011000001010100011000 )
#628
0#
#629
1#
b00000011000000010000000000000000 &
b00100000000100010000010100000000 (
b00101010000111110010000100010100 )
#630
0#
#631
1#
b00000000000000000000000000000000 &
b00001100000001000000000000000000 (
b00011100001001000001101100001010 )
#632
0#
#633
1#
b00000010000000000000000000000000 &
b00000000000000000000000000000000 (
b00100100001100100010011100000101 )
#634
0#
#635
1#
b00000000000000000000000000000000 &
b00100100000111010000111000000010 )
#636
0#
#637
1#
b00011100000010010000011000000000 )
#638
0#
#639
1#
b00001011000001000000000000000000 )
#640
0#
#641
1#
b00000100000000000000000000000000 )
